<core:FragmentDefinition xmlns="sap.m"
	xmlns:f="sap.ui.layout.form" 
	xmlns:core="sap.ui.core" 
	xmlns:l="sap.ui.layout"
	>
	<Dialog xmlns="sap.m" title="Goods Receipt"
			class="sapUiSizeCompact" contentWidth="20%" contentHieght="20%">
		<content>
			<l:Grid defaultSpan="L12 M12 S12" width="auto" position="Center">
				<l:content>
					<!-- <f:SimpleForm maxContainerCols="1"
							editable="true" layout="ResponsiveGridLayout" 
							labelSpanL="2"
							labelSpanM="2" emptySpanL="0" emptySpanM="0" 
							columnsL="2" columnsM="2"
							>
						<f:content> -->
						 <RadioButtonGroup id="rbg2" valueState="Warning" columns = "2" selectedIndex="0" value="{NoDuesQuesetionTblJMode>Answer}">
							<buttons>
								<RadioButton id="RB2-1" text="Casing" width="7rem"/>
								<RadioButton id="RB2-2" text="Tread Pattern"/>
							</buttons>
						</RadioButtonGroup>
						<!-- </f:content>
					</f:SimpleForm> -->
				</l:content>
			</l:Grid>
			
		</content>
			<beginButton>
				<Button text="OK" press="OnOK" />
			</beginButton>
			<endButton>
				<Button text="Cancel" press="OnCancel" />
			</endButton>
	</Dialog>
</core:FragmentDefinition>